rh_sec_data/__init__.py
rh_sec_data/api.py
rh_sec_data/cli.py
rh_sec_data-0.0.2.dist-info/LICENSE
rh_sec_data-0.0.2.dist-info/METADATA
rh_sec_data-0.0.2.dist-info/WHEEL
rh_sec_data-0.0.2.dist-info/entry_points.txt
rh_sec_data-0.0.2.dist-info/top_level.txt
rh_sec_data-0.0.2.dist-info/RECORD
