Metadata-Version: 2.1
Name: rh-sec-data
Version: 0.0.2
Summary: Red Hat Security Data API
Home-page: https://github.com/digitronik/rh-sec-data
Author: Nikhil Dhandre
Author-email: ndhandre@redhat.com
License: UNKNOWN
Platform: UNKNOWN
Classifier: Natural Language :: English
Classifier: Programming Language :: Python :: 3.6
Classifier: Programming Language :: Python :: 3.7
Classifier: Programming Language :: Python :: 3.8
Classifier: Programming Language :: Python :: 3.9
Classifier: Intended Audience :: Developers
Classifier: Intended Audience :: Information Technology
Classifier: License :: OSI Approved :: GNU General Public License v3 (GPLv3)
Requires-Dist: click
Requires-Dist: requests
Provides-Extra: dev
Requires-Dist: pre-commit ; extra == 'dev'
Requires-Dist: pytest ; extra == 'dev'
Requires-Dist: pytest-cov ; extra == 'dev'
Provides-Extra: test
Requires-Dist: pytest ; extra == 'test'
Requires-Dist: pytest-cov ; extra == 'test'
